autest/__init__.py
autest/__main__.py
autest/glb.py
autest/api/__init__.py
autest/api/condition.py
autest/api/filetype.py
autest/api/instance.py
autest/api/reporter.py
autest/api/setup.py
autest/api/test.py
autest/api/testenity.py
autest/api/testers.py
autest/api/testrun.py
autest/api/version.py
autest/api/when.py
autest/common/__init__.py
autest/common/constructor.py
autest/common/disk.py
autest/common/event.py
autest/common/execfile.py
autest/common/is_a.py
autest/common/listalgo.py
autest/common/namespace.py
autest/common/ospath.py
autest/common/process.py
autest/common/reg.py
autest/common/settings.py
autest/common/sort.py
autest/common/task.py
autest/common/version.py
autest/common/win32.py
autest/conditions/__init__.py
autest/conditions/isplatform.py
autest/conditions/process.py
autest/conditions/regkey.py
autest/core/__init__.py
autest/core/conditions.py
autest/core/debug.py
autest/core/delayeventmapper.py
autest/core/engine.py
autest/core/eventinfo.py
autest/core/item.py
autest/core/metaclass.py
autest/core/order.py
autest/core/process.py
autest/core/report.py
autest/core/runable.py
autest/core/runtesttask.py
autest/core/setup.py
autest/core/setupitem.py
autest/core/streamwriter.py
autest/core/stringdict.py
autest/core/test.py
autest/core/testentity.py
autest/core/testerset.py
autest/core/testrun.py
autest/core/variables.py
autest/exceptions/__init__.py
autest/exceptions/killonfailure.py
autest/exceptions/setuperror.py
autest/reporters/__init__.py
autest/reporters/default.py
autest/runlogic/__init__.py
autest/runlogic/process.py
autest/runlogic/runlogic.py
autest/runlogic/test.py
autest/runlogic/testrun.py
autest/setupitems/__init__.py
autest/setupitems/chown.py
autest/setupitems/copy_items.py
autest/setupitems/copyas.py
autest/setupitems/git.py
autest/setupitems/lambdaitem.py
autest/setupitems/makedir.py
autest/setupitems/run_command.py
autest/setupitems/svn.py
autest/testenities/__init__.py
autest/testenities/directory.py
autest/testenities/disk.py
autest-1.10.5.dist-info/METADATA
autest-1.10.5.dist-info/WHEEL
autest-1.10.5.dist-info/entry_points.txt
autest-1.10.5.dist-info/license.txt
autest-1.10.5.dist-info/top_level.txt
autest-1.10.5.dist-info/RECORD
