Metadata-Version: 2.1
Name: autest
Version: 1.10.5
Summary: Reusable gold file testing system
Home-page: https://bitbucket.org/autestsuite/reusable-gold-testing-system
Author: Jason Kenny
Author-email: dragon512@live.com
License: MIT
Platform: UNKNOWN
Classifier: Development Status :: 5 - Production/Stable
Classifier: Environment :: Console
Classifier: Intended Audience :: Developers
Classifier: License :: OSI Approved :: MIT License
Classifier: Operating System :: OS Independent
Classifier: Programming Language :: Python :: 3
Classifier: Programming Language :: Python :: 3.6
Classifier: Programming Language :: Python :: 3.7
Classifier: Programming Language :: Python :: 3.8
Classifier: Programming Language :: Python :: 3.9
Classifier: Programming Language :: Python :: 3.10
Classifier: Programming Language :: Python :: 3.11
Classifier: Topic :: Software Development :: Testing
Classifier: Topic :: Terminals
License-File: license.txt
Requires-Dist: colorama
Requires-Dist: future
Requires-Dist: psutil
